zipsearch/FastSearchEngine.py
zipsearch/FastZipcode.py
zipsearch/__init__.py
zipsearch/boilerplate.py
zipsearch/state_abbr.py
zipsearch/utils.py
zipsearch/bin/__init__.py
zipsearch/bin/indices.bin
zipsearch-1.1.0.dist-info/METADATA
zipsearch-1.1.0.dist-info/WHEEL
zipsearch-1.1.0.dist-info/licenses/LICENSE.txt
zipsearch-1.1.0.dist-info/RECORD
