Metadata-Version: 2.4
Name: zipsearch
Version: 1.1.0
Summary: Updated efficient lookup based on uszipcode
Project-URL: Source, https://github.com/Kydoimos97/zipsearch
Author: kydoimos97
License-File: LICENSE.txt
Requires-Python: >=3.11
